{
  "score": 5.5,
  "issues": [
    {
      "severity": "P0",
      "desc": "merge_writers 所有 echo 日志输出到 stdout，$(merge_writers) 捕获多行字符串导致 build_app cd 必定失败，每轮构建均不可用"
    },
    {
      "severity": "P1",
      "desc": "audit_writer_diff 仅用 git diff --name-only HEAD，untracked 新文件完全绕过越界审计"
    },
    {
      "severity": "P1",
      "desc": "BEST_ROUND 仅在 ACCEPTED 时更新，全部拒绝时 BEST_ROUND=0，连续5轮失败回退逻辑永不触发"
    },
    {
      "severity": "P1",
      "desc": "cmd_status 重复定义（L670 与 L932），第一个为死代码"
    },
    {
      "severity": "P1",
      "desc": "PREV_MEDIAN 空值时 Python float('') 抛 ValueError，set -e 下脚本终止"
    },
    {
      "severity": "P2",
      "desc": "archive_round 复制 bdd-specs.md 路径错误，归档静默丢失 BDD 规格"
    },
    {
      "severity": "P2",
      "desc": "build_app 用 cd 改变全局 CWD，cleanup 后操作在已删除目录中执行"
    }
  ],
  "summary": "14/17 BDD 通过、bash -n 合格，但 P0 stdout 污染导致每轮构建必定失败，无法满足无人值守跑 50 轮的核心目标"
}